mgl_efis_plotter
