Metadata-Version: 1.1
Name: mgl-efis-plotter
Version: 0.2.0
Summary: MGL EFIS data plotter
Home-page: https://github.com/azemon/mgl_efis_plotter
Author: Art Zemon
Author-email: art@zemon.name
License: MIT
Platform: UNKNOWN
Classifier: Development Status :: 4 - Beta
Classifier: Intended Audience :: End Users/Desktop
Classifier: License :: OSI Approved :: MIT License
Classifier: Programming Language :: Python :: 3.6
Classifier: Topic :: Scientific/Engineering :: Information Analysis
Classifier: Topic :: Software Development :: Libraries :: Python Modules
